LICENSE
MANIFEST.in
README.md
setup.py
django_webmoney_merchant.egg-info/PKG-INFO
django_webmoney_merchant.egg-info/SOURCES.txt
django_webmoney_merchant.egg-info/dependency_links.txt
django_webmoney_merchant.egg-info/not-zip-safe
django_webmoney_merchant.egg-info/top_level.txt
webmoney_merchant/__init__.py
webmoney_merchant/admin.py
webmoney_merchant/forms.py
webmoney_merchant/models.py
webmoney_merchant/signals.py
webmoney_merchant/urls.py
webmoney_merchant/views.py
webmoney_merchant/locale/ru/LC_MESSAGES/django.mo
webmoney_merchant/locale/ru/LC_MESSAGES/django.po
webmoney_merchant/management/__init__.py
webmoney_merchant/management/commands/__init__.py
webmoney_merchant/management/commands/wm_invoice_clean.py
webmoney_merchant/migrations/0001_initial.py
webmoney_merchant/migrations/__init__.py
webmoney_merchant/templates/webmoney_merchant/fail.html
webmoney_merchant/templates/webmoney_merchant/success.html