Metadata-Version: 1.1
Name: django-webmoney-merchant
Version: 1.0.3
Summary: WebMoney Merchant Interface for Django.
Home-page: https://github.com/evstropov/django-webmoney_merchant-merchant
Author: Evstropov Nikita
Author-email: evstropov.n@gmail.com
License: UNKNOWN
Platform: UNKNOWN
Classifier: Environment :: Web Environment
Classifier: Intended Audience :: Developers
Classifier: License :: OSI Approved :: Apache Software License
Classifier: Operating System :: OS Independent
Classifier: Programming Language :: Python :: 2.7
Classifier: Framework :: Django
